[
  {
    "id": 1,
    "word": "author",
    "meaning": "yazar"
  },
  {
    "id": 2,
    "word": "decision",
    "meaning": "karar, kararlılık"
  },
  {
    "id": 3,
    "word": "blackboard",
    "meaning": "kara tahta"
  },
  {
    "id": 4,
    "word": "wave",
    "meaning": "el sallamak, dalgalanmak"
  },
  {
    "id": 5,
    "word": "vital",
    "meaning": "önemli, enerji dolu, yaşamsal"
  },
  {
    "id": 6,
    "word": "shoot",
    "meaning": "ateş etmek, gol atmak, fotoğraf çekmek"
  },
  {
    "id": 7,
    "word": "importance",
    "meaning": "önem"
  },
  {
    "id": 8,
    "word": "target",
    "meaning": "hedef, amaç"
  },
  {
    "id": 9,
    "word": "tremendous",
    "meaning": "çok büyük"
  },
  {
    "id": 10,
    "word": "sunbathe",
    "meaning": "güneşlenmek"
  },
  {
    "id": 11,
    "word": "opinion",
    "meaning": "fikir, yargı"
  },
  {
    "id": 12,
    "word": "beach",
    "meaning": "plaj"
  },
  {
    "id": 13,
    "word": "union",
    "meaning": "birlik, sendika"
  },
  {
    "id": 14,
    "word": "solar",
    "meaning": "güneş"
  }
]
